py_jupedsim.cp310-win_amd64.pyd
jupedsim/__init__.py
jupedsim/agent.py
jupedsim/distributions.py
jupedsim/geometry.py
jupedsim/geometry_utils.py
jupedsim/journey.py
jupedsim/library.py
jupedsim/recording.py
jupedsim/routing.py
jupedsim/serialization.py
jupedsim/simulation.py
jupedsim/sqlite_serialization.py
jupedsim/stages.py
jupedsim/internal/aabb.py
jupedsim/internal/grid.py
jupedsim/internal/notebook_utils.py
jupedsim/internal/tracing.py
jupedsim/models/__init__.py
jupedsim/models/anticipation_velocity_model.py
jupedsim/models/collision_free_speed.py
jupedsim/models/collision_free_speed_v2.py
jupedsim/models/generalized_centrifugal_force.py
jupedsim/models/social_force.py
jupedsim/native/__init__.py
jupedsim-1.3.1.data/scripts/jupedsim-visualizer
jupedsim-1.3.1.dist-info/licenses/LICENSE
jupedsim_visualizer/__init__.py
jupedsim_visualizer/config.py
jupedsim_visualizer/geometry.py
jupedsim_visualizer/geometry_widget.py
jupedsim_visualizer/grid.py
jupedsim_visualizer/main_window.py
jupedsim_visualizer/move_controller.py
jupedsim_visualizer/replay_widget.py
jupedsim_visualizer/trajectory.py
jupedsim_visualizer/view_geometry_widget.py
jupedsim-1.3.1.dist-info/METADATA
jupedsim-1.3.1.dist-info/WHEEL
jupedsim-1.3.1.dist-info/top_level.txt
jupedsim-1.3.1.dist-info/RECORD
