Metadata-Version: 2.4
Name: jupedsim
Version: 1.3.1
Summary: JuPedSim is an open source pedestrian dynamics simulator
Home-page: https://www.jupedsim.org
Maintainer: JuPedSim Development Core Team
Maintainer-email: dev@jupedsim.org
Project-URL: Documentation, https://www.jupedsim.org
Project-URL: Source, https://github.com/PedestrianDynamics/jupedsim
Project-URL: Tracker, https://github.com/PedestrianDynamics/jupedsim/issues
Classifier: Development Status :: 4 - Beta
Classifier: License :: OSI Approved :: GNU Lesser General Public License v3 or later (LGPLv3+)
Classifier: Operating System :: Microsoft :: Windows
Classifier: Operating System :: Unix
Classifier: Operating System :: MacOS
Classifier: Natural Language :: English
Classifier: Programming Language :: C++
Classifier: Programming Language :: C
Classifier: Programming Language :: Python :: 3 :: Only
Classifier: Programming Language :: Python :: 3
Classifier: Programming Language :: Python :: 3.10
Classifier: Programming Language :: Python :: 3.11
Classifier: Programming Language :: Python :: 3.12
Classifier: Programming Language :: Python :: 3.13
Classifier: Intended Audience :: Developers
Classifier: Intended Audience :: Science/Research
Requires-Python: >=3.10,<3.14
License-File: LICENSE
Requires-Dist: numpy~=2.2
Requires-Dist: shapely~=2.0
Requires-Dist: pyside6~=6.8
Requires-Dist: vtk~=9.4
Requires-Dist: deprecated~=1.2.18
Dynamic: classifier
Dynamic: description
Dynamic: description-content-type
Dynamic: home-page
Dynamic: license-file
Dynamic: maintainer
Dynamic: maintainer-email
Dynamic: project-url
Dynamic: requires-dist
Dynamic: requires-python
Dynamic: summary
